.gitignore
CHANGES.rst
LICENSE.txt
README.rst
config.rb
setup.cfg
setup.py
sass/ie.sass
sass/print.sass
sass/screen.sass
zilch/__init__.py
zilch/client.py
zilch/exc.py
zilch/middleware.py
zilch/recorder.py
zilch/script.py
zilch/store.py
zilch/utils.py
zilch/web.py
zilch.egg-info/PKG-INFO
zilch.egg-info/SOURCES.txt
zilch.egg-info/dependency_links.txt
zilch.egg-info/entry_points.txt
zilch.egg-info/not-zip-safe
zilch.egg-info/requires.txt
zilch.egg-info/top_level.txt
zilch/static/stylesheets/ie.css
zilch/static/stylesheets/print.css
zilch/static/stylesheets/screen.css
zilch/templates/common.mak
zilch/templates/layout.mak
zilch/templates/group/index.mak
zilch/templates/group/layout.mak
zilch/templates/group/show.mak
zilch/tests/__init__.py
zilch/tests/test_client.py
zilch/tests/test_store.py
zilch/tests/test_web.py
zilch/tests/utils.py