Metadata-Version: 1.0
Name: zilch
Version: 0.1.3
Summary: Error/Exception collector and reporter
Home-page: https://github.com/bbangert/zilch
Author: Ben Bangert
Author-email: ben@groovie.org
License: MIT
Keywords: zeromq exceptions errors reporter collector sqlalchemy
Platform: UNKNOWN
Classifier: Intended Audience :: Developers
Classifier: Programming Language :: Python
